{
  "miniprogramRoot": "dist/",
  "projectname": "bjut-cats",
  "description": "北京工业大学BJUT小动物观赏协会猫咪图鉴",
  "appid": "wxa932a8008de3fd40",
  "setting": {
    "urlCheck": true,
    "es6": false,
    "enhance": false,
    "compileHotReLoad": false,
    "postcss": false,
    "minified": false,
    "babelSetting": {
      "ignore": [],
      "disablePlugins": [],
      "outputPath": ""
    },
    "condition": false
  },
  "compileType": "miniprogram",
  "libVersion": "2.32.3",
  "srcMiniprogramRoot": "dist/",
  "packOptions": {
    "ignore": [],
    "include": []
  },
  "condition": {},
  "editorSetting": {
    "tabIndent": "insertSpaces",
    "tabSize": 2
  }
}